synthetick/__init__.py
synthetick/emitter.py
synthetick/price_feed.py
synthetick/price_time_series.py
synthetick/synthetick.py
synthetick-0.4.0.dist-info/METADATA
synthetick-0.4.0.dist-info/WHEEL
synthetick-0.4.0.dist-info/RECORD
