Metadata-Version: 2.4
Name: synthetick
Version: 0.4.0
Summary: Synthetic price production utility for historical and live data (WIP).
Project-URL: Homepage, https://github.com/mchiuminatto/synthetick
Project-URL: Issues, https://github.com/mchiuminatto/synthetick/issues
Author-email: Marcello Chiuminatto <mch@thequantick.net>
Classifier: License :: OSI Approved :: MIT License
Classifier: Operating System :: OS Independent
Classifier: Programming Language :: Python :: 3
Requires-Python: >=3.11
Requires-Dist: asyncio>=3
Requires-Dist: matplotlib>=3.8
Requires-Dist: mplfinance>=0.12
Requires-Dist: numpy>=1.26
Requires-Dist: pandas>=2
Requires-Dist: pyarrow>=13.0
